Workbook

Sheet How to use
A1: Activity 1.1.3 - how to run your own 45-minute monitoring session
A2: IMPORTANT: the Worked Example sheet contains a CONSTRUCTED illustrative dataset about Nordtre AS, the fictional company used in Activities 1.1.1 and 1.1.2. It is not observed data and no real person wrote any of it. It exists to show the shape of a complete answer. Your own submission must use a real brand and your own observations, because the activity asks for firsthand experience. Presenting invented posts as observed feedback would be the data-integrity failure this lesson warns about.
A4: Step | B4: Do this | C4: Why it matters
A5: 1 | B5: Pick a brand or product you know, and write down WHY you picked it | C5: Your familiarity is a bias as well as an advantage. Recording it lets a reader weigh your reading of ambiguous posts.
A6: 2 | B6: Choose two platforms, not one, and write down which | C6: Every platform has a different user base and a different complaint culture. Two lets you see whether a theme is real or platform-specific.
A7: 3 | B7: Write your search terms down BEFORE you start | C7: Searching 'brand problems' and searching 'brand review' return different populations. Deciding after you see results is selective evaluation.
A8: 4 | B8: Read the Coding Rules sheet and agree your own tie-breakers | C8: Consistency between your first and last twenty items is what makes the tally meaningful.
A9: 5 | B9: Set a timer for 45 minutes and capture into the Capture Sheet as you go | C9: Coding from memory afterwards produces a summary of what you remember, which over-weights the vivid items.
A10: 6 | B10: Record every item you see in the window, including boring ones | C10: Skipping neutral posts inflates both tails and is the most common way this exercise goes wrong.
A11: 7 | B11: Stop when the timer stops, then count | C11: A fixed window makes the sample defensible. Stopping when you have enough of what you expected does not.
A12: 8 | B12: Fill in the Analysis sheet and read the limitations before writing your report | C12: The limitations are half the marks in an evaluation course.
A14: What this exercise can and cannot support
A15: Can | B15: Identify recurring THEMES and generate hypotheses worth testing | C15: Themes repeat across independent posters, which is real signal
A16: Can | B16: Detect a sudden CHANGE if you repeat the same search later | C16: Same terms, same platforms, same window makes two sessions comparable
A17: Cannot | B17: State the LEVEL of customer satisfaction | C17: Social media is the most self-selected source there is: people post when delighted or furious, and the satisfied middle never appears
A18: Cannot | B18: Support a percentage as a population estimate | C18: Your 58 posts are not a random sample of customers, so 50% positive describes your 58 posts and nothing more

Sheet Coding Rules
A1: Sentiment coding frame - decide these BEFORE you start reading
A2: A tally is only meaningful if the same post would get the same code on Monday and on Friday. These rules make that likely. Write down any tie-breaker you invent during the session.
A4: Code | B4: Assign when | C4: Worked edge cases
A5: Positive | B5: The poster expresses satisfaction, praise, or would recommend | C5: 'Solid build, worth the price' = positive. 'Better than I expected' = positive even though it implies low expectations.
A6: Negative | B6: The poster expresses dissatisfaction, a problem, or would not recommend | C6: 'Took three weeks to arrive' = negative even if stated calmly. Tone does not decide the code; the experience does.
A7: Neutral | B7: A question, a factual statement, or a comparison with no evaluation | C7: 'Does it fit a 120cm desk?' = neutral. 'Costs more than IKEA' = neutral unless the poster says that is bad.
A8: Mixed | B8: Praise and complaint in the same post | C8: Code the PRIMARY point and note the secondary in the theme column. Do not count one post twice in the sentiment tally.
A10: Rules that prevent the three common coding failures
A11: One post, one code | B11: Never let a single post contribute to two sentiment categories | C11: Otherwise the total exceeds the number of posts and every percentage is wrong
A12: Code the experience, not the tone | B12: A politely worded complaint is negative; an enthusiastic question is neutral | C12: Tone-based coding drifts with your mood across a 45-minute session
A13: Capture as you go | B13: Code each item when you read it, not from memory afterwards | C13: Memory over-weights the vivid, which is exactly the bias this lesson opened with
A14: Record the boring ones | B14: Neutral posts are data | C14: Skipping them inflates both tails and is the single most common error in this exercise
A16: A self-consistency check worth running
A17: When you finish, re-code the first ten items without looking at your original codes. If more than one or two differ, your rules were not tight enough and the tally is softer than it looks. This is the individual version of inter-rater reliability, and reporting that you ran it is worth more than a clean-looking number that was never checked.

Sheet Capture Sheet
A1: Capture sheet - fill this in DURING your session
A2: One row per item. Do not summarise; capture. The Analysis sheet counts whatever is here.
A4: Session details
A5: Brand or product | E5: and why you chose it
A6: Platforms used | E6: two, not one
A7: Search terms | E7: written down before starting
A8: Date and time window | E8: e.g. 14 Sep 2026, 19:00-19:45
A9: Minutes spent | E9: 45
A11: # | B11: Platform | C11: Sentiment | D11: Theme | E11: What was said (your paraphrase) | F11: Secondary theme
A12: 1
A13: 2
A14: 3
A15: 4
A16: 5
A17: 6
A18: 7
A19: 8
A20: 9
A21: 10
A22: 11
A23: 12
... A71: 60
A73: Paraphrase rather than quoting verbatim where you can. It keeps the focus on the theme, and it avoids reproducing an identifiable individual's words in a submitted document.

Sheet Worked Example
A1: WORKED EXAMPLE - constructed illustrative data, not observed
A2: CONSTRUCTED DATA. These 58 items are invented for teaching purposes and describe Nordtre AS, the fictional company from Activities 1.1.1 and 1.1.2. No real person wrote any of them, and no real brand is described. Use this to see the shape of a complete answer; collect your own for your submission.
A4: # | B4: Platform | C4: Sentiment | D4: Theme | E4: Paraphrase
A5: 1 | B5: Reddit | C5: Positive | D5: Timber and build quality | E5: Solid oak, feels far sturdier than flat-pack usually does
A6: 2 | B6: Reddit | C6: Positive | D6: Timber and build quality | E6: Solid oak, feels far sturdier than flat-pack usually does
A7: 3 | B7: Reddit | C7: Positive | D7: Timber and build quality | E7: Solid oak, feels far sturdier than flat-pack usually does
A8: 4 | B8: Reddit | C8: Positive | D8: Timber and build quality | E8: Solid oak, feels far sturdier than flat-pack usually does
A9: 5 | B9: Reddit | C9: Positive | D9: Timber and build quality | E9: Solid oak, feels far sturdier than flat-pack usually does
A10: 6 | B10: Reddit | C10: Positive | D10: Timber and build quality | E10: Solid oak, feels far sturdier than flat-pack usually does
A11: 7 | B11: Instagram | C11: Positive | D11: Timber and build quality | E11: Grain looks great in the photos and in person
A12: 8 | B12: Instagram | C12: Positive | D12: Timber and build quality | E12: Grain looks great in the photos and in person
A13: 9 | B13: Instagram | C13: Positive | D13: Timber and build quality | E13: Grain looks great in the photos and in person
A14: 10 | B14: Instagram | C14: Positive | D14: Timber and build quality | E14: Grain looks great in the photos and in person
A15: 11 | B15: Instagram | C15: Positive | D15: Timber and build quality | E15: Grain looks great in the photos and in person
A16: 12 | B16: Reddit | C16: Positive | D16: Assembly experience | E16: Instructions actually made sense, assembled in 20 minutes
... A62: 58 | B62: Instagram | C62: Neutral | D62: Comparison question | E62: How does this compare to the Danish brands?

Sheet Analysis
A1: Steps 3 and 4 - analysis of the worked example
A2: Every count is a live COUNTIF over the Worked Example sheet, so it recomputes if you paste your own captured data over it.
A4: Step 3: sentiment tally
A5: Category | B5: Count | C5: Share | D5: Formula | E5: Note
A6: Positive | B6: =COUNTIF('Worked Example'!$C$5:$C$62,A6) | C6: =B6/$B$9*100 | D6: =COUNTIF(sentiment range, "Positive")
A7: Negative | B7: =COUNTIF('Worked Example'!$C$5:$C$62,A7) | C7: =B7/$B$9*100 | D7: =COUNTIF(sentiment range, "Negative")
A8: Neutral | B8: =COUNTIF('Worked Example'!$C$5:$C$62,A8) | C8: =B8/$B$9*100 | D8: =COUNTIF(sentiment range, "Neutral")
A9: Total items captured | B9: =SUM(B6:B8) | E9: Must equal the number of rows captured. One post, one code
A11: Net sentiment (positive % - negative %) | B11: =C6-C7 | D11: =Positive share - Negative share | E11: Same construction as NPS, and it inherits the same weakness: it hides the neutrals
A13: Step 3: theme frequency
A14: Theme | B14: Count | C14: Share | D14: Sentiment | E14: Why it matters
A15: Timber and build quality | B15: =COUNTIF('Worked Example'!$D$5:$D$62,A15) | C15: =B15/$B$9*100 | D15: Positive | E15: The product promise is landing. Protect it
A16: Assembly experience | B16: =COUNTIF('Worked Example'!$D$5:$D$62,A16) | C16: =B16/$B$9*100 | D16: Positive | E16: A differentiator against flat-pack expectations
A17: Sustainability credentials | B17: =COUNTIF('Worked Example'!$D$5:$D$62,A17) | C17: =B17/$B$9*100 | D17: Positive | E17: Named as a purchase REASON, not just a nice-to-have
A18: Customer service | B18: =COUNTIF('Worked Example'!$D$5:$D$62,A18) | C18: =B18/$B$9*100 | D18: Positive | E18: Recovery works when something goes wrong
A19: Delivery time | B19: =COUNTIF('Worked Example'!$D$5:$D$62,A19) | C19: =B19/$B$9*100 | D19: Negative | E19: Largest single complaint theme. Ties to the on-time delivery KPI
A20: Missing hardware | B20: =COUNTIF('Worked Example'!$D$5:$D$62,A20) | C20: =B20/$B$9*100 | D20: Negative | E20: A quality-control problem with a measurable cost in resends
A21: Price versus alternatives | B21: =COUNTIF('Worked Example'!$D$5:$D$62,A21) | C21: =B21/$B$9*100 | D21: Negative | E21: Positioning, not a defect. Answerable with messaging
A22: Checkout problems | B22: =COUNTIF('Worked Example'!$D$5:$D$62,A22) | C22: =B22/$B$9*100 | D22: Negative | E22: SMALL COUNT, LARGE MEANING - see the note below
A23: Fit and dimensions question | B23: =COUNTIF('Worked Example'!$D$5:$D$62,A23) | C23: =B23/$B$9*100 | D23: Neutral | E23: Product pages are not answering an obvious question
A24: Price question | B24: =COUNTIF('Worked Example'!$D$5:$D$62,A24) | C24: =B24/$B$9*100 | D24: Neutral | E24: Low value, but free to answer
A25: Comparison question | B25: =COUNTIF('Worked Example'!$D$5:$D$62,A25) | C25: =B25/$B$9*100 | D25: Neutral | E25: Consideration-stage interest
A26: Total | B26: =SUM(B15:B25) | E26: Cross-check: must equal the sentiment total
A28: Frequency is not importance
A29: Delivery time is mentioned 9 times and checkout problems only twice. The checkout theme is still the more actionable finding, because Activity 1.1.2 measured D2C conversion at 1.16% and falling 12% year on year while sessions rose 38%. Two posts describing failed card payments are the qualitative CAUSE of a quantitative effect already costing measurable revenue. The quantitative half supplies the size; the qualitative half supplies the cause. Ranking themes by count alone would have buried it.
A31: Platform split - is a theme real, or one platform's culture?
A32: Platform | B32: Items | C32: Share | D32: Formula | E32: Note
A33: Reddit | B33: =COUNTIF('Worked Example'!$B$5:$B$62,A33) | C33: =B33/$B$9*100 | D33: =COUNTIF(platform range, "Reddit")
A34: Instagram | B34: =COUNTIF('Worked Example'!$B$5:$B$62,A34) | C34: =B34/$B$9*100 | D34: =COUNTIF(platform range, "Instagram")
A35: Negative items on Reddit | B35: =COUNTIFS('Worked Example'!$B$5:$B$62,"Reddit",'Worked Example'!$C$5:$C$62,"Negative") | E35: Complaint culture differs sharply by platform, which is exactly why two platforms were used
A36: Negative items on Instagram | B36: =COUNTIFS('Worked Example'!$B$5:$B$62,"Instagram",'Worked Example'!$C$5:$C$62,"Negative")
A38: Limitations that must be stated with any figure above
A39: Self-selection | B39: People post when delighted or furious | C39: The satisfied middle is invisible, so 50% positive describes these 58 posts and not the customer base
A40: Not a random sample | B40: Search terms and platforms determined what was found | C40: No percentage here estimates a population value
A41: Single 45-minute window | B41: One session cannot separate a trend from a bad week | C41: Repeat with identical terms and window to make two sessions comparable
A42: Single coder | B42: All coding decisions are one person's judgement | C42: Re-coding the first ten items blind is the cheapest available check
A43: Visible themes only | B43: A problem nobody posts about is absent from this data | C43: Pair with a source that reaches the middle, such as a post-purchase survey

Sheet Method and Rationale
A1: Why the method was designed this way
A3: Decision | B3: What was chosen | C3: Why | D3: What was rejected, and why
A4: Data provenance | B4: A constructed dataset, clearly labelled, about a fictional company | C4: The activity requires firsthand observation, which cannot be delegated. A labelled teaching example shows the shape of a complete answer without anyone presenting invented posts as observed feedback. | D4: Inventing plausible posts about a real brand and presenting them as monitoring results. That is the data-integrity failure this lesson explicitly warns about.
A5: Two platforms | B5: Reddit and Instagram | C5: Complaint culture differs sharply between platforms. Two lets you see whether a theme is real or an artefact of one community's norms. | D5: One platform: a theme appearing only there cannot be distinguished from that platform's culture.
A6: Search terms fixed in advance | B6: Written down before the session | C6: Searching 'brand problems' and 'brand review' return different populations. Choosing terms after seeing results is selective evaluation. | D6: Adjusting terms mid-session to find more of what you expected.
A7: Coding rules fixed in advance | B7: A written frame with worked edge cases | C7: A tally is meaningful only if the same post gets the same code on Monday and Friday. | D7: Coding by feel: the codes drift across a 45-minute session and the tally quietly becomes a mood record.
A8: One post, one code | B8: Mixed posts get their primary point coded, secondary noted as a theme | C8: Otherwise the sentiment total exceeds the number of posts and every share is wrong. | D8: Counting a mixed post in two categories.
A9: Code the experience, not the tone | B9: A politely worded complaint is negative | C9: Tone-based coding tracks the poster's manner rather than what happened to them. | D9: Coding on how angry the post sounds.
A10: Capture during, not after | B10: Fill the sheet as each item is read | C10: Coding from memory over-weights the vivid, which is the exact bias this lesson opened with. | D10: Reading for 45 minutes then summarising: that produces a record of what you remember.
A11: Neutral items recorded | B11: Questions and factual comparisons are captured | C11: Skipping them inflates both tails and is the most common error in this exercise. | D11: Recording only positives and negatives, which is easier and wrong.
A12: Themes ranked by meaning, not count | B12: Checkout problems flagged despite only two mentions | C12: Those two are the qualitative cause of the conversion-rate decline measured in Activity 1.1.2, so they attach to a quantified revenue effect. Frequency is not importance. | D12: Ranking purely by count, which would have buried the most actionable finding under delivery complaints.
A13: Self-consistency check | B13: Re-code the first ten items blind at the end | C13: It is the single-coder version of inter-rater reliability, and it costs five minutes. | D13: Reporting a clean tally that was never checked.
