Workbook

Sheet Business Profile
A1: Nordtre AS - Business Profile (hypothetical)
A3: Business name | B3: Nordtre AS
A4: Industry | B4: Sustainable home and office furniture
A5: Founded | B5: 2021, Trondheim, Norway
A6: Products | B6: Flat-pack desks, shelving and chairs in FSC-certified Norwegian timber | C6: Plus refinishing and spare-part kits
A7: Target market | B7: Urban Norwegian households and small businesses, ages 28-45 | C7: Environmentally motivated, home-office buyers
A8: Channels | B8: 1) D2C webshop 2) Retail partnerships 3) B2B contract fit-out
A9: Average headcount | B9: 34 | C9: Production and warehouse 19, design and commercial 15
A10: Reporting currency | B10: NOK
A11: Reporting period | B11: FY2026, compared against FY2025
A13: Why these three channels matter for the KPI analysis
A14: - | B14: The three channels have very different unit economics, so a single blended figure hides more than it shows.
A15: - | B15: D2C is high volume and low order value. B2B is low volume and high contract value.
A16: - | B16: Retail partnerships carry the lowest gross margin because the partner takes a share.
A17: - | B17: Every KPI in this workbook is therefore reported by channel wherever the data allows it.

Sheet Financial KPIs
A1: Financial KPIs - FY2026
A3: Description | B3: Amount (NOK) | C3: Formula / note | D3: Evaluation note
A4: Step 2a: Sales revenue sources
A5: D2C e-commerce | B5: 7200000 | C5: Own webshop | D5: 3,000 orders x NOK 2,400 AOV
A6: Retail partnerships | B6: 6900000 | C6: Interior stores, wholesale terms
A7: B2B contract sales | B7: 4300000 | C7: Office fit-outs for SMEs
A8: Total Revenue | B8: =SUM(B5:B7) | C8: =SUM(B5:B7)
A10: Step 2b: Costs and profit margins
A11: Cost of goods sold | B11: 10120000 | C11: Timber, hardware, manufacturing
A12: Gross Profit | B12: =B8-B11 | C12: =B8-B11
A13: Gross Margin (%) | B13: =B12/B8*100 | C13: =B12/B8*100 | D13: The margin the channels actually differ on
A15: Marketing | B15: 2300000 | C15: Brand plus acquisition
A16: Salaries and personnel | B16: 3100000
A17: Logistics and fulfilment | B17: 640000
A18: Other operating costs | B18: 400000 | C18: Rent, software, insurance
A19: Total operating expenses | B19: =SUM(B15:B18) | C19: =SUM(B15:B18)
A20: Total Expenses | B20: =B11+B19 | C20: =B11+B19
A22: Operating Profit (EBIT) | B22: =B8-B20 | C22: =B8-B20
A23: Operating Margin (%) | B23: =B22/B8*100 | C23: =B22/B8*100 | D23: The margin management is judged on
A24: Corporate tax at 22% | B24: =B22*0.22 | C24: =B22*0.22
A25: Net Profit | B25: =B22-B24 | C25: =B22-B24
A26: Net Margin (%) | B26: =B25/B8*100 | C26: =B25/B8*100 | D26: The margin the owners keep
A28: Which margin? All three, because they answer different questions
A29: Gross, operating and net margin differ by a factor of nearly six here. Quoting 'profit margin' without naming the variant makes any comparison meaningless.
A31: Step 2c: Return on Investment
A32: Investment: CNC line and webshop replatform | B32: 3000000 | C32: Committed Q1 FY2026
A33: Incremental annual operating profit from it | B33: 780000 | C33: Attributed to this investment only | D33: Not total company profit
A34: ROI, year 1 (%) | B34: =B33/B32*100 | C34: =B33/B32*100
A35: Payback period (years) | B35: =B32/B33 | C35: =B32/B33
A36: Cumulative ROI over 3 years (%) | B36: =(B33*3-B32)/B32*100 | C36: =(B33*3-B32)/B32*100 | D36: Still negative: payback is not yet reached
A38: Two deliberate method choices on ROI
A39: 1. The numerator is the INCREMENTAL profit attributable to the investment, not total company net profit. Dividing whole-business profit by one investment credits that investment with everything the company did.
A40: 2. Both the one-year and three-year figures are shown. A single-horizon ROI can be made to look like anything, so the horizon must be stated alongside the number.

Sheet Non-Financial KPIs
A1: Non-Financial KPIs - FY2026 vs FY2025
A3: Step 3a: Customer Acquisition Cost, by segment
A4: Segment | B4: FY2026 spend | C4: FY2026 new customers | D4: FY2026 CAC | E4: Note
A5: D2C | B5: 890000 | C5: 8900 | D5: =B5/C5 | E5: Paid social and search
A6: B2B contract | B6: 700000 | C6: 140 | D6: =B6/C6 | E6: Field sales, trade fairs, long cycle
A7: Blended | B7: =SUM(B5:B6) | C7: =SUM(C5:C6) | D7: =B7/C7 | E7: Total spend / total customers, NOT the average of the two CACs
A9: Segment | B9: FY2025 spend | C9: FY2025 new customers | D9: FY2025 CAC | E9: Note
A10: D2C | B10: 651000 | C10: 6200 | D10: =B10/C10
A11: B2B contract | B11: 924000 | C11: 210 | D11: =B11/C11
A12: Blended | B12: =SUM(B10:B11) | C12: =SUM(C10:C11) | D12: =B12/C12
A14: Change in blended CAC (%) | B14: =(B7/C7-B12/C12)/(B12/C12)*100 | C14: =(FY26 CAC - FY25 CAC) / FY25 CAC | D14: Looks like a large efficiency gain
A16: Step 3a continued: lifetime value, because CAC alone is not interpretable
A17: Segment | B17: Avg order/contract | C17: Gross margin | D17: Orders per lifetime | E17: Lifetime value (NOK)
A18: D2C | B18: 2400 | C18: 0.45 | D18: 1.6 | E18: =B18*C18*D18
A19: B2B contract | B19: 78000 | C19: 0.38 | D19: 2.2 | E19: =B19*C19*D19
A21: LTV:CAC ratio, D2C | B21: =E18/D5 | C21: =LTV / CAC | D21: Healthy is normally above 3x
A22: LTV:CAC ratio, B2B | B22: =E19/D6 | C22: =LTV / CAC
A24: Total lifetime value acquired FY2026 | B24: =C5*E18+C6*E19 | C24: =D2C customers x D2C LTV + B2B customers x B2B LTV
A25: Total lifetime value acquired FY2025 | B25: =C10*E18+C11*E19 | C25: Same LTV assumptions applied to FY2025 volumes
A26: Change in acquired lifetime value (%) | B26: =(B24-B25)/B25*100 | C26: =(FY26 - FY25) / FY25 | D26: THE FINDING: essentially flat
A28: Step 3b: Website traffic monitoring
A29: Metric | B29: FY2026 | C29: FY2025 | D29: Change | E29: Monitoring strategy
A30: Monthly sessions | B30: 21500 | C30: 15600 | D30: =(B30-C30)/C30*100 | E30: GA4, segmented by source: organic, paid, email, referral
A31: Monthly unique visitors | B31: 14800 | C31: 11200 | D31: =(B31-C31)/C31*100 | E31: Reach, not activity. Tracked separately from sessions
A32: Avg session duration (min) | B32: 3.4 | C32: 3.9 | D32: =(B32-C32)/C32*100 | E32: Falling duration with rising traffic suggests lower intent
A33: Monthly D2C orders | B33: 250 | C33: 207 | D33: =(B33-C33)/C33*100 | E33: From the order system, not analytics
A34: Conversion rate (%) | B34: =B33/B30*100 | C34: =C33/C30*100 | D34: =(B34-C34)/C34*100 | E34: THE FINDING: traffic up sharply, conversion down. Traffic alone is a vanity metric
A36: Step 3c: Employee turnover
A37: Measure | B37: Departures | C37: Avg headcount | D37: Rate (%) | E37: Note
A38: Company total | B38: 7 | C38: 34 | D38: =B38/C38*100 | E38: The headline figure
A39: Production and warehouse | B39: 5 | C39: 19 | D39: =B39/C39*100 | E39: Burnout during launch peaks
A40: Design and commercial | B40: 2 | C40: 15 | D40: =B40/C40*100 | E40: Low rate, but both were senior designers
A41: Regretted departures only | B41: 4 | C41: 34 | D41: =B41/C41*100 | E41: The figure that actually matters
A43: Cost per replacement (recruit + train) | B43: 95000 | C43: Estimate
A44: Total replacement cost FY2026 | B44: =B43*B38 | C44: =cost x departures
A45: As share of operating profit (%) | B45: =B44/'Financial KPIs'!B22*100 | C45: =B44 / Operating Profit x 100 | E45: THE LINK: a non-financial KPI priced in financial terms

Sheet KPI Interactions
A1: Step 4: How the KPIs interact
A3: Interaction | B3: What the numbers show | C3: What it means for the business
A4: CAC -> mix -> LTV | B4: Blended CAC fell 28% while total acquired lifetime value was flat (+0.4%) and customer count rose 41%. | C4: The CAC improvement is a mix artefact. Acquisition shifted toward cheap, low-LTV D2C customers while B2B new accounts fell 33% and B2B CAC rose 14%. The company is working much harder for the same lifetime value.
A5: Traffic -> conversion -> revenue | B5: Sessions rose 38% but conversion fell from 1.33% to 1.16%, so orders rose only 21%. Session duration fell 13%. | C5: Traffic is being bought faster than it can be converted. Conversion rate is the intermediary KPI; without it, the traffic number reads as growth when it is partly waste.
A6: Turnover -> cost -> margin | B6: 7 departures at NOK 95,000 replacement cost is NOK 665,000, equal to 36% of operating profit. | C6: A non-financial KPI with a direct, quantifiable claim on the financial ones. Reducing regretted turnover is a margin lever, not only an HR matter.
A7: Turnover -> product -> D2C revenue | B7: Design turnover is only 13.3%, but both leavers were senior product designers. | C7: The low departmental rate hides the risk. The product pipeline feeds D2C revenue, so this is a leading indicator of a future revenue problem.
A8: Margin variant -> decision | B8: Gross 45.0%, operating 10.0%, net 7.8%. | C8: Any target, bonus or channel comparison stated as 'profit margin' is ambiguous until the variant is named. The three differ by nearly six times.
A9: ROI -> horizon | B9: Year-1 ROI is 26%, but payback is 3.8 years so cumulative 3-year ROI is still -22%. | C9: A positive-looking annual ROI can sit on top of an investment that has not yet repaid itself. The horizon must be stated with the number.
A11: Most crucial KPIs for Nordtre, with justification
A12: KPI | B12: Why it is crucial here | C12: Why the obvious alternative is weaker
A13: Gross margin by channel | B13: The three channels have different economics, and channel mix is the main driver of blended margin. | C13: Blended gross margin can stay flat while a profitable channel shrinks and a thin one grows.
A14: LTV:CAC by segment | B14: It is the only form in which acquisition efficiency is interpretable, and it exposes the mix shift. | C14: Blended CAC moved 28% for reasons that had nothing to do with efficiency.
A15: D2C conversion rate | B15: It is the intermediary between the traffic being paid for and the revenue actually earned. | C15: Website traffic on its own rose 38% while contributing far less than that to revenue.
A16: Regretted turnover in design | B16: It is a leading indicator for the product pipeline that D2C revenue depends on. | C16: Company-wide turnover of 20.6% averages away the two departures that matter most.

Sheet Checks
A1: Reconciliation checks
A2: Every check below must read OK. These exist because the most damaging spreadsheet errors are syntactically valid formulas pointing at the wrong cells, which no data-quality rule will catch.
A4: Check | B4: Expected | C4: Result | D4: Why this check exists
A5: Revenue channels sum to Total Revenue | B5: ='Financial KPIs'!B5+'Financial KPIs'!B6+'Financial KPIs'!B7 | C5: =IF('Financial KPIs'!B8=B5,"OK","FAIL") | D5: Catches a SUM range that misses a row
A6: COGS + operating expenses = Total Expenses | B6: ='Financial KPIs'!B11+'Financial KPIs'!B19 | C6: =IF('Financial KPIs'!B20=B6,"OK","FAIL") | D6: Catches double counting between the two cost blocks
A7: D2C orders x AOV = D2C revenue | B7: ='Non-Financial KPIs'!B33*12*'Non-Financial KPIs'!B18 | C7: =IF(ROUND('Financial KPIs'!B5,0)=ROUND(B7,0),"OK","FAIL") | D7: Independent route to the same figure, which is data ensembling in miniature
A8: Blended CAC is not the average of segment CACs | B8: =AVERAGE('Non-Financial KPIs'!D5,'Non-Financial KPIs'!D6) | C8: =IF(ROUND('Non-Financial KPIs'!D7,2)<>ROUND(B8,2),"OK","CHECK") | D8: A very common error: averaging two CACs ignores that one segment has 64x the volume
A9: Gross margin is above operating margin | B9: n/a | C9: =IF('Financial KPIs'!B13>'Financial KPIs'!B23,"OK","FAIL") | D9: Sanity rule: a lower gross than operating margin means a reference error
A11: Errors found in the supplied Activity 1.1.1 workbook
A12: Cell | B12: Formula as supplied | C12: Computes | D12: Should be
A13: 'Financial KPIs'!B14 (ROI) | B13: =B2/B3*100 | C13: Online Sales / Retail Sales = 150% | D13: =B12/B13*100 -> 133.3%, which is what the report text states
A14: 'Financial KPIs'!B19 (CAC) | B14: =B2/B3 | C14: Online Sales / Retail Sales = 1.5 | D14: =B17/B18 -> 30, which is what the report text states
A16: Both formulas were copied from the first block without adjusting the cell references. This is a logic error: the syntax is valid, the output is a plausible number, and no data-quality check would flag it. It is exactly the error class that the reconciliation checks above are designed to catch.

Sheet Formula Reference
A1: Formula reference - every calculation used, and when to reach for it
A2: The Excel column shows the formula exactly as it appears in this workbook. The General column is the one to memorise, because cell references change between tasks.
A4: KPI | B4: Excel formula used here | C4: General formula | D4: Reach for it when | E4: Most common error
A5: REVENUE AND MARGIN
A6: Total revenue | B6: =SUM(B5:B7) | C6: Sum of all revenue streams | D6: Always the starting figure of a financial analysis | E6: SUM range not extended after a new channel is inserted
A7: Gross profit | B7: =B8-B11 | C7: Revenue - Cost of goods sold | D7: Judging product or channel profitability | E7: Putting operating expenses into COGS, which understates gross margin
A8: Gross margin % | B8: =B12/B8*100 | C8: Gross profit / Revenue x 100 | D8: Comparing products, channels or suppliers | E8: Dividing by COGS instead of revenue
A9: Operating profit (EBIT) | B9: =B8-B20 | C9: Revenue - Total expenses | D9: Judging how well the company is run | E9: Forgetting that COGS is part of total expenses, so it is subtracted twice or not at all
A10: Operating margin % | B10: =B22/B8*100 | C10: Operating profit / Revenue x 100 | D10: Management performance, budget targets | E10: Quoting it as 'profit margin' next to someone else's gross margin
A11: Net profit | B11: =B22-B24 | C11: Operating profit - tax (and interest) | D11: What the owners actually retain | E11: Reporting pre-tax profit and calling it net
A12: Net margin % | B12: =B25/B8*100 | C12: Net profit / Revenue x 100 | D12: Bottom-line profitability, investor reporting | E12: Mixing margin variants inside one comparison
A13: INVESTMENT
A14: ROI % | B14: =B33/B32*100 | C14: Gain from investment / Cost of investment x 100 | D14: Capital allocation decisions | E14: Using TOTAL company profit as the gain, which credits one investment with everything
A15: Payback period | B15: =B32/B33 | C15: Investment / Annual return | D15: Always, alongside ROI, to expose the horizon | E15: Omitting it, so a slow investment looks fast
A16: Cumulative ROI % | B16: =(B33*3-B32)/B32*100 | C16: (Annual return x years - Investment) / Investment x 100 | D16: Multi-year appraisal of one investment | E16: Assuming an annual ROI simply multiplies or compounds
A17: ACQUISITION
A18: CAC | B18: =B5/C5 | C18: Acquisition spend / New customers acquired | D18: Evaluating marketing efficiency, per segment | E18: Using total marketing spend, which includes brand and retention work
A19: Blended CAC | B19: =B7/C7 | C19: TOTAL spend / TOTAL customers | D19: Only ever alongside the segment figures | E19: Taking the AVERAGE of segment CACs, which ignores volume differences
A20: Lifetime value (LTV) | B20: =B18*C18*D18 | C20: Avg order value x Gross margin x Purchases per lifetime | D20: Whenever CAC is reported, since CAC alone is uninterpretable | E20: Using revenue instead of gross profit, which overstates LTV
A21: LTV:CAC ratio | B21: =E18/D5 | C21: LTV / CAC | D21: Judging whether acquisition is sustainable (above 3x is the rule of thumb) | E21: Computing it blended, which hides a mix shift
A22: TRAFFIC
A23: Conversion rate % | B23: =B33/B30*100 | C23: Orders / Sessions x 100 | D23: Every single time website traffic is reported | E23: Taking orders and sessions from two systems that count differently
A24: CHANGE AND RATES
A25: Percentage change | B25: =(B24-B25)/B25*100 | C25: (New - Old) / Old x 100 | D25: Any period-on-period comparison | E25: Dividing by the NEW value, which understates the change
A26: Employee turnover % | B26: =B38/C38*100 | C26: Departures / Average headcount x 100 | D26: Organisational health, segmented by team and by regretted status | E26: Using closing headcount instead of average, which distorts a growing company
A27: Cost as share of profit % | B27: =B44/'Financial KPIs'!B22*100 | C27: Cost / Operating profit x 100 | D27: Pricing a non-financial problem in financial terms | E27: Expressing it against revenue, which makes it look trivially small

Sheet Method and Rationale
A1: Why each figure in this workbook was calculated the way it was
A2: An evaluation is only checkable if the reasoning behind each choice is written down. This sheet records every methodological decision, the alternative that was rejected, and why.
A4: Decision | B4: What I chose | C4: Why | D4: What I rejected, and why
A5: Business design | B5: Three channels with deliberately different unit economics | C5: A single-channel business makes every blended KPI correct by accident. The whole point of the activity is that blended figures hide things, which only shows up when the underlying segments differ. | D5: One channel: the analysis in Step 4 would have had nothing to find.
A6: Which profit margin | B6: Reported all three: gross 45.0%, operating 10.0%, net 7.8% | C6: The lesson states that a higher margin means more is retained per unit earned, but 'profit margin' is ambiguous. Showing all three makes the ambiguity concrete: they differ by nearly six times here. | D6: A single 'profit margin' figure: it would be unusable for any comparison, and picking the flattering one is selective evaluation.
A7: ROI numerator | B7: Incremental operating profit attributable to the investment (NOK 780,000) | C7: ROI measures the return of a specific investment. Only profit caused by that investment belongs in the numerator. | D7: Total company net profit divided by the investment: this credits one machine with revenue the whole company generated. It is the most common way a reported ROI is inflated.
A8: ROI horizon | B8: Year-1 ROI, payback period, and cumulative 3-year ROI together | C8: Year 1 shows +26% while the cumulative 3-year figure is -22%, because payback is 3.85 years. Both are arithmetically correct, so quoting only one is a choice that changes the decision. | D8: A single ROI figure: an ROI without a stated horizon is not an evaluable number.
A9: CAC granularity | B9: CAC per segment first, blended second and clearly labelled | C9: D2C CAC is NOK 100 and B2B is NOK 5,000. A blended figure describes neither customer and moves whenever the mix moves, independently of any efficiency change. | D9: Blended CAC as the headline: it fell 28% this year for reasons unrelated to marketing performance.
A10: Blended CAC method | B10: Total spend divided by total customers | C10: This is the only correct way to blend. The segments have very different volumes, so they must be weighted by customer count. | D10: The average of the two segment CACs (NOK 2,550): wrong by a factor of fourteen, because it treats 8,900 and 140 customers as equally important. A reconciliation check on the Checks sheet tests for this.
A11: Adding LTV | B11: Lifetime value per segment, and the LTV:CAC ratio | C11: The lesson states that a low CAC relative to lifetime value indicates a healthy business model, so CAC is defined relative to LTV. Without it, a falling CAC cannot be told apart from a shift to cheaper, less valuable customers. | D11: Reporting CAC alone: the activity would then have concluded 'CAC improved', which the data does not support.
A12: LTV formula | B12: Average order value x GROSS MARGIN x purchases per lifetime | C12: Lifetime value should represent contribution, not turnover. Using gross margin makes LTV comparable to CAC, which is also a cost. | D12: Average order value x purchases: this overstates LTV by more than double here and would make any LTV:CAC ratio meaningless.
A13: The CAC finding | B13: Compared total lifetime value acquired across both years, holding LTV assumptions constant | C13: Holding LTV constant isolates the effect of the MIX change. Total acquired value was flat (+0.4%) while customer count rose 41% and blended CAC fell 28%, which proves the CAC improvement is a mix artefact. | D13: Comparing blended CAC alone: it would have supported the opposite conclusion.
A14: Traffic metrics | B14: Sessions, unique visitors and session duration tracked separately, plus conversion rate | C14: The lesson names distinctive visitors, page views and average session duration as separate insights. They measure reach, activity and depth, and here they move by different amounts. | D14: A single 'traffic' number: it rose 38% while orders rose 21%, so the single number would have read as growth that did not happen.
A15: Order source | B15: Orders taken from the order system, not from web analytics | C15: Two independent sources for the same figure is data ensembling in miniature. Agreement raises confidence and disagreement locates a tagging error. | D15: Analytics-only conversion tracking: it is lossy, and a single source cannot be reconciled against anything.
... A20: Documentation notes | B20: Stored as literal text, not as live formulas | C20: A note reading '=B8-B11' assigned normally becomes a live formula and silently computes something wrong. Every documentation cell here is forced to text type. | D20: Writing notes normally: an early draft of this workbook had 15 documentation cells silently evaluating as formulas.
